rankeval/VERSION
rankeval/__init__.py
rankeval/.libs/libgomp-3300acd3.so.1.0.0
rankeval/dataset/dataset_container.py
rankeval/dataset/write_json_dataset_catalogue.py
rankeval/dataset/_svmlight_format.cpp
rankeval/dataset/svmlight_format.py
rankeval/dataset/dataset.py
rankeval/dataset/datasets_fetcher.py
rankeval/dataset/__init__.py
rankeval/dataset/_svmlight_format.cpython-37m-x86_64-linux-gnu.so
rankeval/analysis/_efficient_topological.cpython-37m-x86_64-linux-gnu.so
rankeval/analysis/_efficient_feature_impl.cpp
rankeval/analysis/_efficient_feature_impl.h
rankeval/analysis/feature.py
rankeval/analysis/_efficient_topological.pyx
rankeval/analysis/_efficient_feature.cpython-37m-x86_64-linux-gnu.so
rankeval/analysis/effectiveness.py
rankeval/analysis/statistical.py
rankeval/analysis/_efficient_feature.pyx
rankeval/analysis/__init__.py
rankeval/analysis/topological.py
rankeval/visualization/feature.py
rankeval/visualization/effectiveness.py
rankeval/visualization/__init__.py
rankeval/visualization/topological.py
rankeval/model/proxy_Jforests.py
rankeval/model/rt_ensemble.py
rankeval/model/proxy_XGBoost.py
rankeval/model/proxy_CatBoost.py
rankeval/model/proxy_ScikitLearn.py
rankeval/model/__init__.py
rankeval/model/proxy_LightGBM.py
rankeval/model/proxy_QuickRank.py
rankeval/test/base.py
rankeval/test/__init__.py
rankeval/test/dataset/test_dataset.py
rankeval/test/dataset/test_svmlight_format.py
rankeval/test/dataset/__init__.py
rankeval/test/analysis/test_feature.py
rankeval/test/analysis/__init__.py
rankeval/test/analysis/test_statistical.py
rankeval/test/data/ScikitLearn.model.txt
rankeval/test/data/LightGBM.model.txt
rankeval/test/data/Jforests.model.xml
rankeval/test/data/svmlight_classification_qid.txt
rankeval/test/data/msn1.fold1.train.5k.txt
rankeval/test/data/svmlight_classification.txt
rankeval/test/data/CatBoost.model.coreml
rankeval/test/data/svmlight_invalid.txt
rankeval/test/data/quickrank.model.xml
rankeval-0.8.2.dist-info/top_level.txt
rankeval-0.8.2.dist-info/RECORD
rankeval-0.8.2.dist-info/METADATA
rankeval-0.8.2.dist-info/WHEEL
