Metadata-Version: 2.1
Name: rankeval
Version: 0.8.2
Summary: Tool for the analysis and evaluation of Learning to Rank models based on ensembles of regression trees.
Home-page: http://rankeval.isti.cnr.it
Author: HPC lab, ISTI-CNR
Author-email: rankeval@isti.cnr.it
License: MPL 2.0
Download-URL: http://pypi.python.org/pypi/rankeval
Keywords: Learning to Rank,Model Analysis,Model Evaluation,Ensemble of Regression Trees
Platform: any
Classifier: Development Status :: 5 - Production/Stable
Classifier: Environment :: Console
Classifier: Framework :: Jupyter
Classifier: Intended Audience :: Science/Research
Classifier: License :: OSI Approved :: Mozilla Public License 2.0 (MPL 2.0)
Classifier: Operating System :: OS Independent
Classifier: Programming Language :: Python :: 2.7
Classifier: Programming Language :: Python :: 3.5
Classifier: Programming Language :: Python :: 3.6
Classifier: Programming Language :: Python :: 3.7
Classifier: Topic :: Scientific/Engineering :: Artificial Intelligence
Classifier: Topic :: Scientific/Engineering :: Information Analysis
Classifier: Topic :: Scientific/Engineering :: Visualization
Classifier: Topic :: Software Development :: Libraries :: Python Modules
Classifier: Topic :: System :: Benchmark
Requires-Python: >=2.7, !=3.0.*, !=3.1.*, !=3.2.*, !=3.3.*, <4
Provides-Extra: develop
Requires-Dist: numpy (>=1.13)
Requires-Dist: scipy (>=0.14.0)
Requires-Dist: six (>=1.9.0)
Requires-Dist: pandas (>=0.19.1)
Requires-Dist: xarray (>=0.10.9)
Requires-Dist: seaborn (>=0.8)
Requires-Dist: matplotlib (>=2.0.2)
Provides-Extra: develop
Requires-Dist: sphinx (>=1.5.0); extra == 'develop'
Requires-Dist: sphinx-rtd-theme (>=0.2.0); extra == 'develop'
Requires-Dist: numpydoc (>0.5.0); extra == 'develop'
